tuyapower/__init__.py
tuyapower/__main__.py
tuyapower-0.2.0.dist-info/LICENSE
tuyapower-0.2.0.dist-info/METADATA
tuyapower-0.2.0.dist-info/WHEEL
tuyapower-0.2.0.dist-info/top_level.txt
tuyapower-0.2.0.dist-info/RECORD
