Metadata-Version: 2.1
Name: tuyapower
Version: 0.2.0
Summary: Pull power and state data from Tuya WiFi smart devices
Home-page: https://github.com/jasonacox/tuyapower
Author: Jason Cox
Author-email: jason@jasonacox.com
License: UNKNOWN
Platform: UNKNOWN
Classifier: Programming Language :: Python :: 2
Classifier: Programming Language :: Python :: 3
Classifier: License :: OSI Approved :: MIT License
Classifier: Operating System :: OS Independent
License-File: LICENSE
Requires-Dist: tinytuya
